httpx_rate_limiter_transport/__init__.py
httpx_rate_limiter_transport/limit.py
httpx_rate_limiter_transport/py.typed
httpx_rate_limiter_transport/transport.py
httpx_rate_limiter_transport/utils.py
httpx_rate_limiter_transport-0.4.2.dist-info/licenses/LICENSE
httpx_rate_limiter_transport-0.4.2.dist-info/METADATA
httpx_rate_limiter_transport-0.4.2.dist-info/WHEEL
httpx_rate_limiter_transport-0.4.2.dist-info/top_level.txt
httpx_rate_limiter_transport-0.4.2.dist-info/RECORD
