Metadata-Version: 2.4
Name: httpx-rate-limiter-transport
Version: 0.4.2
Summary: Async transport for httpx to implement various rate limiting (using a centralized redis as backend)
Project-URL: Homepage, https://github.com/fabien-marty/httpx-rate-limiter-transport
Project-URL: Repository, https://github.com/fabien-marty/httpx-rate-limiter-transport.git
Requires-Python: >=3.10
License-File: LICENSE
Requires-Dist: async-redis-rate-limiters>=0.1.2
Requires-Dist: httpx>=0.28.1
Requires-Dist: redis>=6.2.0
Requires-Dist: stlog>=0.5.0
Dynamic: license-file
